{"lang": "en_US", "eventid": "act49side", "eventName": "First of A Thousand Autumns", "entryType": "ACTIVITY", "storyCode": "TA-7", "avgTag": "After Operation", "storyName": "Severed Yearning", "storyInfo": "Deceived by White's words to 'eliminate the great evil before dealing with the culprit', Chun encourages Jie to die on Wang's behalf. Jie entrusts her writing knife to Jun before she departs.\n", "storyList": [{"id": 0, "prop": "HEADER", "attributes": {"key": "title_test", "is_skippable": "true", "fit_mode": "BLACK_MASK"}}, {"id": 1, "prop": "Blocker", "attributes": {"a": 1.0, "r": 0.0, "g": 0.0, "b": 0.0, "fadetime": 0.0, "block": "true"}}, {"id": 2, "prop": "stopmusic", "attributes": {}}, {"id": 3, "prop": "Dialog", "attributes": {}}, {"id": 4, "prop": "Delay", "attributes": {"time": 1.0}}, {"id": 5, "prop": "Background", "attributes": {"image": "25_g11_yanroom", "screenadapt": "coverall"}}, {"id": 6, "prop": "Blocker", "attributes": {"a": 0.0, "r": 0.0, "g": 0.0, "b": 0.0, "fadetime": 1.0, "block": "true"}}, {"id": 7, "prop": "Delay", "attributes": {"time": 2.0}}, {"id": 8, "prop": "animtext", "attributes": {"content": "<p=1>Year 982</>", "id": "at1", "name": "group_location_stamp", "style": "avg_only_heavy", "pos": "-400,-200", "block": "false", "p": 1.0}}, {"id": 9, "prop": "delay", "attributes": {"time": 3.0}}, {"id": 10, "prop": "animtextclean", "attributes": {}}, {"id": 11, "prop": "delay", "attributes": {"time": 1.0}}, {"id": 12, "prop": "playMusic", "attributes": {"intro": "$drift_intro", "key": "$drift_loop", "volume": 0.6}}, {"id": 13, "prop": "CameraShake", "attributes": {"duration": 0.3, "xstrength": 2.0, "ystrength": 5.0, "vibrato": 10.0, "randomness": 90.0, "fadeout": "true", "block": "false"}}, {"id": 14, "prop": "playsound", "attributes": {"key": "$d_avg_swordcrack"}}, {"id": 15, "prop": "Delay", "attributes": {"time": 1.0}}, {"id": 16, "prop": "charslot", "attributes": {"slot": "m", "name": "avgnew_2014_nian_1#8$1", "duration": 1.0}}, {"id": 17, "prop": "Delay", "attributes": {"time": 2.0}}, {"id": 18, "prop": "name", "attributes": {"content": "Damn, it's just a sword. How could this be screwed up? Getting rusty?", "name": "Nian"}, "figure_art": "avgnew_2014_nian_1#8$1"}, {"id": 19, "prop": "charslot", "attributes": {"slot": "m", "focus": "n"}}, {"id": 20, "prop": "name", "attributes": {"content": "The smith scratches her head in confusion and takes out another steel ingot from storage."}}, {"id": 21, "prop": "charslot", "attributes": {"slot": "m", "name": "avgnew_2014_nian_1#2$1"}}, {"id": 22, "prop": "name", "attributes": {"content": "Autumn is wet this year. It's suffocating.", "name": "Nian"}, "figure_art": "avgnew_2014_nian_1#2$1"}, {"id": 23, "prop": "charslot", "attributes": {"slot": "m", "name": "avgnew_2014_nian_1#6$1"}}, {"id": 24, "prop": "name", "attributes": {"content": "Something doesn't feel right...", "name": "Nian"}, "figure_art": "avgnew_2014_nian_1#6$1"}, {"id": 25, "prop": "Dialog", "attributes": {}}, {"id": 26, "prop": "Blocker", "attributes": {"a": 1.0, "r": 0.0, "g": 0.0, "b": 0.0, "fadetime": 2.0, "block": "true"}}, {"id": 27, "prop": "charslot", "attributes": {}}, {"id": 28, "prop": "delay", "attributes": {"time": 1.0}}, {"id": 29, "prop": "Background", "attributes": {"image": "bg_cottage", "screenadapt": "coverall"}}, {"id": 30, "prop": "Blocker", "attributes": {"a": 0.0, "r": 0.0, "g": 0.0, "b": 0.0, "fadetime": 2.0, "block": "true"}}, {"id": 31, "prop": "delay", "attributes": {"time": 1.0}}, {"id": 32, "prop": "CameraShake", "attributes": {"duration": 0.5, "xstrength": 15.0, "ystrength": 15.0, "vibrato": 30.0, "randomness": 90.0, "fadeout": "true", "block": "false"}}, {"id": 33, "prop": "PlaySound", "attributes": {"key": "$d_gen_thunders_amb", "volume": 1.0}}, {"id": 34, "prop": "Blocker", "attributes": {"a": 0.0, "r": 255.0, "g": 255.0, "b": 255.0, "fadetime": 0.0, "block": "true"}}, {"id": 35, "prop": "Blocker", "attributes": {"a": 1.0, "r": 255.0, "g": 255.0, "b": 255.0, "fadetime": 0.03, "block": "true"}}, {"id": 36, "prop": "Blocker", "attributes": {"a": 0.0, "r": 255.0, "g": 255.0, "b": 255.0, "fadetime": 0.5, "block": "true"}}, {"id": 37, "prop": "Blocker", "attributes": {"a": 1.0, "r": 1.0, "g": 1.0, "b": 1.0, "fadetime": 0.03, "block": "true"}}, {"id": 38, "prop": "Blocker", "attributes": {"a": 0.0, "r": 0.0, "g": 0.0, "b": 0.0, "fadetime": 0.5, "block": "false"}}, {"id": 39, "prop": "delay", "attributes": {"time": 1.0}}, {"id": 40, "prop": "charslot", "attributes": {"slot": "m", "name": "avgnew_2015_dusk_1#6$1", "duration": 0.5}}, {"id": 41, "prop": "delay", "attributes": {"time": 1.0}}, {"id": 42, "prop": "name", "attributes": {"content": "—!", "name": "Dusk"}, "figure_art": "avgnew_2015_dusk_1#6$1"}, {"id": 43, "prop": "name", "attributes": {"content": "Impossible... this is impossible!", "name": "Dusk"}, "figure_art": "avgnew_2015_dusk_1#6$1"}, {"id": 44, "prop": "charslot", "attributes": {"slot": "m", "name": "avgnew_2015_dusk_1#5$1"}}, {"id": 45, "prop": "name", "attributes": {"content": "Is It... awakening?", "name": "Dusk"}, "figure_art": "avgnew_2015_dusk_1#5$1"}, {"id": 46, "prop": "dialog", "attributes": {}}, {"id": 47, "prop": "charslot", "attributes": {"slot": "m", "name": "avg_npc_143#1"}}, {"id": 48, "prop": "delay", "attributes": {"time": 0.3}}, {"id": 49, "prop": "charslot", "attributes": {"slot": "m", "action": "jump", "posfrom": "0,0", "posto": "0,0", "power": 15.0, "times": 1.0, "duration": 0.3}}, {"id": 50, "prop": "name", "attributes": {"content": "(Worried screech)—?", "name": "Ink Spirit"}, "figure_art": "avg_npc_143#1"}, {"id": 51, "prop": "charslot", "attributes": {}}, {"id": 52, "prop": "name", "attributes": {"content": "An angry cloud has appeared on the calm scroll."}}, {"id": 53, "prop": "dialog", "attributes": {}}, {"id": 54, "prop": "Effect", "attributes": {"name": "$e_vanish", "layer": 1.0, "y": 600.0}}, {"id": 55, "prop": "Effect", "attributes": {"name": "$e_vanish", "layer": 1.0, "x": 550.0}}, {"id": 56, "prop": "delay", "attributes": {"time": 0.3}}, {"id": 57, "prop": "CameraShake", "attributes": {"duration": 0.3, "xstrength": 15.0, "ystrength": 15.0, "vibrato": 30.0, "randomness": 90.0, "fadeout": "true", "block": "false"}}, {"id": 58, "prop": "PlaySound", "attributes": {"key": "$d_gen_thunders_amb", "volume": 1.0}}, {"id": 59, "prop": "Blocker", "attributes": {"a": 1.0, "r": 1.0, "g": 1.0, "b": 1.0, "fadetime": 0.03, "block": "true"}}, {"id": 60, "prop": "Blocker", "attributes": {"a": 0.0, "r": 0.0, "g": 0.0, "b": 0.0, "fadetime": 1.0, "block": "false"}}, {"id": 61, "prop": "name", "attributes": {"content": "A crack of thunder leaves an ink trail on the white scroll, looking decidedly out of place."}}, {"id": 62, "prop": "name", "attributes": {"content": "Countless terrible ink spirits appear out of nowhere, scattering across the scroll, covering everything on it in black ink."}}, {"id": 63, "prop": "charslot", "attributes": {"slot": "m", "name": "avgnew_2015_dusk_1#3$1"}}, {"id": 64, "prop": "name", "attributes": {"content": "I didn't paint this...", "name": "Dusk"}, "figure_art": "avgnew_2015_dusk_1#3$1"}, {"id": 65, "prop": "CameraShake", "attributes": {"duration": 0.3, "xstrength": 30.0, "ystrength": 30.0, "vibrato": 30.0, "randomness": 90.0, "fadeout": "true", "block": "false"}}, {"id": 66, "prop": "charslot", "attributes": {"slot": "m", "name": "avgnew_2015_dusk_1#5$1"}}, {"id": 67, "prop": "name", "attributes": {"content": "Go... away!", "name": "Dusk"}, "figure_art": "avgnew_2015_dusk_1#5$1"}, {"id": 68, "prop": "dialog", "attributes": {}}, {"id": 69, "prop": "charslot", "attributes": {}}, {"id": 70, "prop": "CameraShake", "attributes": {"duration": 1.5, "xstrength": 20.0, "ystrength": 20.0, "vibrato": 30.0, "randomness": 90.0, "fadeout": "true", "block": "false"}}, {"id": 71, "prop": "PlaySound", "attributes": {"key": "$p_imp_ancientsword_s", "volume": 0.6}}, {"id": 72, "prop": "Dialog", "attributes": {}}, {"id": 73, "prop": "Blocker", "attributes": {"a": 1.0, "r": 0.0, "g": 0.0, "b": 0.0, "fadetime": 2.0, "block": "true"}}, {"id": 74, "prop": "charslot", "attributes": {}}, {"id": 75, "prop": "delay", "attributes": {"time": 1.0}}, {"id": 76, "prop": "playsound", "attributes": {"key": "$d_avg_rainlight_loop", "loop": "true", "channel": "r", "volume": 0.0}}, {"id": 77, "prop": "SoundVolume", "attributes": {"volume": 1.0, "channel": "r", "fadetime": 2.0}}, {"id": 78, "prop": "bgeffect", "attributes": {"name": "$eb_rain", "layer": 1.0}}, {"id": 79, "prop": "Background", "attributes": {"image": "35_g11_yumendesert", "screenadapt": "coverall"}}, {"id": 80, "prop": "Blocker", "attributes": {"a": 0.0, "r": 0.0, "g": 0.0, "b": 0.0, "fadetime": 2.0, "block": "true"}}, {"id": 81, "prop": "delay", "attributes": {"time": 1.0}}, {"id": 82, "prop": "PlaySound", "attributes": {"key": "$d_avg_sandftsingle", "volume": 0.7}}, {"id": 83, "prop": "charslot", "attributes": {"slot": "m", "name": "avg_2024_chyue_1#1$1", "duration": 0.5}}, {"id": 84, "prop": "delay", "attributes": {"time": 1.5}}, {"id": 85, "prop": "charslot", "attributes": {"slot": "m", "name": "avg_npc_1637_1#1$1"}}, {"id": 86, "prop": "name", "attributes": {"content": "You've had a long journey, Mr. Shuo.", "name": "Baizao Soldier"}, "figure_art": "avg_npc_1637_1#1$1"}, {"id": 87, "prop": "name", "attributes": {"content": "I will take you to a quiet place where you can rest.", "name": "Baizao Soldier"}, "figure_art": "avg_npc_1637_1#1$1"}, {"id": 88, "prop": "charslot", "attributes": {"slot": "m", "name": "avg_2024_chyue_1#1$1"}}, {"id": 89, "prop": "name", "attributes": {"content": "I should not delay in reporting to the Ministry of War.", "name": "Shuo"}, "figure_art": "avg_2024_chyue_1#1$1"}, {"id": 90, "prop": "charslot", "attributes": {"slot": "m", "name": "avg_npc_1637_1#1$1"}}, {"id": 91, "prop": "name", "attributes": {"content": "There has been an incident in Baizao. His Majesty commands that you are not to enter for the time being.", "name": "Baizao Soldier"}, "figure_art": "avg_npc_1637_1#1$1"}, {"id": 92, "prop": "charslot", "attributes": {"slot": "m", "name": "avg_2024_chyue_1#6$1"}}, {"id": 93, "prop": "name", "attributes": {"content": "Why?", "name": "Shuo"}, "figure_art": "avg_2024_chyue_1#6$1"}, {"id": 94, "prop": "dialog", "attributes": {}}, {"id": 95, "prop": "charslot", "attributes": {}}, {"id": 96, "prop": "CameraShake", "attributes": {"duration": 1.0, "xstrength": 15.0, "ystrength": 15.0, "vibrato": 30.0, "randomness": 90.0, "fadeout": "true", "block": "false"}}, {"id": 97, "prop": "PlaySound", "attributes": {"key": "$d_gen_thunders_amb", "volume": 1.0}}, {"id": 98, "prop": "Blocker", "attributes": {"a": 1.0, "r": 1.0, "g": 1.0, "b": 1.0, "fadetime": 0.03, "block": "true"}}, {"id": 99, "prop": "Blocker", "attributes": {"a": 0.0, "r": 0.0, "g": 0.0, "b": 0.0, "fadetime": 1.5, "block": "true"}}, {"id": 100, "prop": "charslot", "attributes": {"slot": "m", "name": "avg_2024_chyue_1#8$1"}}, {"id": 101, "prop": "name", "attributes": {"content": "Is that... the Tomb of Sui?", "name": "Shuo"}, "figure_art": "avg_2024_chyue_1#8$1"}, {"id": 102, "prop": "name", "attributes": {"content": "Wang... what have you done?", "name": "Shuo"}, "figure_art": "avg_2024_chyue_1#8$1"}, {"id": 103, "prop": "Dialog", "attributes": {}}, {"id": 104, "prop": "StopSound", "attributes": {"channel": "r", "fadetime": 2.0}}, {"id": 105, "prop": "Blocker", "attributes": {"a": 1.0, "r": 0.0, "g": 0.0, "b": 0.0, "fadetime": 2.0, "block": "true"}}, {"id": 106, "prop": "charslot", "attributes": {}}, {"id": 107, "prop": "bgeffect", "attributes": {}}, {"id": 108, "prop": "delay", "attributes": {"time": 1.0}}, {"id": 109, "prop": "Background", "attributes": {"image": "70_g5_tjtopfloor", "screenadapt": "coverall"}}, {"id": 110, "prop": "Blocker", "attributes": {"a": 0.0, "r": 0.0, "g": 0.0, "b": 0.0, "fadetime": 2.0, "block": "true"}}, {"id": 111, "prop": "delay", "attributes": {"time": 1.0}}, {"id": 112, "prop": "backgroundTween", "attributes": {"xScaleTo": 1.05, "yScaleTo": 1.05, "duration": 1.0, "block": "false"}}, {"id": 113, "prop": "Background", "attributes": {"image": "70_g5_tjtopfloor", "screenadapt": "coverall", "fadetime": 1.0}}, {"id": 114, "prop": "PlaySound", "attributes": {"key": "$d_gen_heartbeat", "volume": 1.0, "channel": "HB", "loop": "true"}}, {"id": 115, "prop": "stopsound", "attributes": {"channel": "HB", "fadetime": 1.0}}, {"id": 116, "prop": "delay", "attributes": {"time": 1.5}}, {"id": 117, "prop": "name", "attributes": {"content": "Did the heart skip a beat, or did it beat twice in an instant?"}}, {"id": 118, "prop": "Dialog", "attributes": {}}, {"id": 119, "prop": "backgroundTween", "attributes": {"xScaleTo": 1.05, "yScaleTo": 1.05, "duration": 1.0, "block": "false"}}, {"id": 120, "prop": "Background", "attributes": {"image": "70_g5_tjtopfloor", "screenadapt": "coverall", "fadetime": 1.0}}, {"id": 121, "prop": "PlaySound", "attributes": {"key": "$d_gen_heartbeat", "volume": 1.0, "channel": "HB", "loop": "true"}}, {"id": 122, "prop": "stopsound", "attributes": {"channel": "HB", "fadetime": 1.0}}, {"id": 123, "prop": "Dialog", "attributes": {}}, {"id": 124, "prop": "delay", "attributes": {"time": 1.5}}, {"id": 125, "prop": "name", "attributes": {"content": "Or was it the vibration of the nomadic city from some sudden movement?"}}, {"id": 126, "prop": "Dialog", "attributes": {}}, {"id": 127, "prop": "backgroundTween", "attributes": {"xScaleTo": 1.05, "yScaleTo": 1.05, "duration": 1.0, "block": "false"}}, {"id": 128, "prop": "Background", "attributes": {"image": "70_g5_tjtopfloor", "screenadapt": "coverall", "fadetime": 1.0}}, {"id": 129, "prop": "PlaySound", "attributes": {"key": "$d_gen_heartbeat", "volume": 1.0, "channel": "HB", "loop": "true"}}, {"id": 130, "prop": "stopsound", "attributes": {"channel": "HB", "fadetime": 1.0}}, {"id": 131, "prop": "Dialog", "attributes": {}}, {"id": 132, "prop": "delay", "attributes": {"time": 1.5}}, {"id": 133, "prop": "name", "attributes": {"content": "Or was it..."}}, {"id": 134, "prop": "CameraShake", "attributes": {"duration": 0.3, "xstrength": 5.0, "ystrength": 10.0, "vibrato": 10.0, "randomness": 90.0, "fadeout": "true", "block": "false"}}, {"id": 135, "prop": "PlaySound", "attributes": {"key": "$d_avg_bookdrop", "volume": 1.0}}, {"id": 136, "prop": "name", "attributes": {"content": "*Plop*"}}, {"id": 137, "prop": "name", "attributes": {"content": "The scroll that was in the proxy's hand is now on the ground."}}, {"id": 138, "prop": "Dialog", "attributes": {}}, {"id": 139, "prop": "charslot", "attributes": {"slot": "m", "name": "avg_npc_2125_1#10$1", "duration": 0.5}}, {"id": 140, "prop": "delay", "attributes": {"time": 1.0}}, {"id": 141, "prop": "name", "attributes": {"content": "Wang?!", "name": "Jie"}, "figure_art": "avg_npc_2125_1#10$1"}, {"id": 142, "prop": "dialog", "attributes": {}}, {"id": 143, "prop": "charslot", "attributes": {}}, {"id": 144, "prop": "playsound", "attributes": {"key": "$rungeneral", "loop": "true", "channel": "bgs"}}, {"id": 145, "prop": "StopSound", "attributes": {"channel": "bgs", "fadetime": 2.0}}, {"id": 146, "prop": "delay", "attributes": {"time": 1.5}}, {"id": 147, "prop": "PlaySound", "attributes": {"key": "$dooropenquite", "volume": 1.0}}, {"id": 148, "prop": "charslot", "attributes": {"slot": "m", "name": "avg_npc_2127_1#5$2", "duration": 0.5}}, {"id": 149, "prop": "delay", "attributes": {"time": 0.5}}, {"id": 150, "prop": "name", "attributes": {"content": "J-Jie!", "name": "Chun"}, "figure_art": "avg_npc_2127_1#5$2"}, {"id": 151, "prop": "charslot", "attributes": {"slot": "m", "name": "avg_npc_2125_1#10$1"}}, {"id": 152, "prop": "name", "attributes": {"content": "What is it?", "name": "Jie"}, "figure_art": "avg_npc_2125_1#10$1"}, {"id": 153, "prop": "charslot", "attributes": {"slot": "m", "name": "avg_npc_2127_1#13$2"}}, {"id": 154, "prop": "name", "attributes": {"content": "Look at this!", "name": "Chun"}, "figure_art": "avg_npc_2127_1#13$2"}, {"id": 155, "prop": "dialog", "attributes": {}}, {"id": 156, "prop": "charslot", "attributes": {"slot": "m", "name": "avg_npc_2125_1#11$1"}}, {"id": 157, "prop": "PlaySound", "attributes": {"key": "$d_avg_paper2", "volume": 1.0}}, {"id": 158, "prop": "delay", "attributes": {"time": 1.0}}, {"id": 159, "prop": "name", "attributes": {"content": "A letter of indictment... for Wang? Who gave you this?", "name": "Jie"}, "figure_art": "avg_npc_2125_1#11$1"}, {"id": 160, "prop": "charslot", "attributes": {"slot": "m", "name": "avg_npc_2127_1#11$2"}}, {"id": 161, "prop": "name", "attributes": {"content": "Someone sent it to the Sui Regulator. The Supervisor had to report to His Majesty. There are rumors that the Imperial Guard is coming to the Sky Mirror Pavilion!", "name": "Chun"}, "figure_art": "avg_npc_2127_1#11$2"}, {"id": 162, "prop": "stopmusic", "attributes": {"fadetime": 2.0}}, {"id": 163, "prop": "Dialog", "attributes": {}}, {"id": 164, "prop": "Blocker", "attributes": {"a": 1.0, "r": 0.0, "g": 0.0, "b": 0.0, "fadetime": 2.0, "block": "true"}}, {"id": 165, "prop": "charslot", "attributes": {}}, {"id": 166, "prop": "delay", "attributes": {"time": 1.0}}, {"id": 167, "prop": "Background", "attributes": {"image": "70_g7_suilingcore", "screenadapt": "coverall"}}, {"id": 168, "prop": "Blocker", "attributes": {"a": 0.0, "r": 0.0, "g": 0.0, "b": 0.0, "fadetime": 2.0, "block": "true"}}, {"id": 169, "prop": "playMusic", "attributes": {"intro": "$m_bat_epic_intro", "key": "$m_bat_epic_loop", "volume": 0.6}}, {"id": 170, "prop": "Effect", "attributes": {"name": "$e_sandfall_01", "layer": 1.0}}, {"id": 171, "prop": "playsound", "attributes": {"key": "$smallearthquake", "volume": 0.6}}, {"id": 172, "prop": "CameraShake", "attributes": {"duration": 2.0, "xstrength": 10.0, "ystrength": 10.0, "vibrato": 30.0, "randomness": 90.0, "fadeout": "true", "block": "false"}}, {"id": 173, "prop": "delay", "attributes": {"time": 3.0}}, {"id": 174, "prop": "Blocker", "attributes": {"a": 0.6, "r": 0.0, "g": 0.0, "b": 0.0, "fadetime": 0.5, "block": "true"}}, {"id": 175, "prop": "Subtitle", "attributes": {"text": "Finally...", "x": 300.0, "y": 370.0, "alignment": "center", "size": 24.0, "delay": 0.04, "width": 700.0}}, {"id": 176, "prop": "Subtitle", "attributes": {"text": "...Finally!", "x": 300.0, "y": 370.0, "alignment": "center", "size": 24.0, "delay": 0.04, "width": 700.0}}, {"id": 177, "prop": "Subtitle", "attributes": {"text": "You're here.", "x": 300.0, "y": 370.0, "alignment": "center", "size": 24.0, "delay": 0.04, "width": 700.0}}, {"id": 178, "prop": "subtitle", "attributes": {}}, {"id": 179, "prop": "Blocker", "attributes": {"a": 0.0, "r": 0.0, "g": 0.0, "b": 0.0, "fadetime": 1.5, "block": "true"}}, {"id": 180, "prop": "charslot", "attributes": {"slot": "m", "name": "avg_2027_wang_1#6$2", "duration": 0.5}}, {"id": 181, "prop": "delay", "attributes": {"time": 1.0}}, {"id": 182, "prop": "name", "attributes": {"content": "Why are you... awake?", "name": "Wang"}, "figure_art": "avg_2027_wang_1#6$2"}, {"id": 183, "prop": "charslot", "attributes": {"slot": "m", "name": "avg_2027_wang_1#12$2"}}, {"id": 184, "prop": "name", "attributes": {"content": "No... no. Your aura is almost identical to Its own, but you've appeared in that hollow visage...", "name": "Wang"}, "figure_art": "avg_2027_wang_1#12$2"}, {"id": 185, "prop": "Dialog", "attributes": {}}, {"id": 186, "prop": "Dialog", "attributes": {}}, {"id": 187, "prop": "Blocker", "attributes": {"a": 0.6, "r": 0.0, "g": 0.0, "b": 0.0, "fadetime": 0.5, "block": "true"}}, {"id": 188, "prop": "Subtitle", "attributes": {"text": "The hollow visage that is also yours.", "x": 300.0, "y": 370.0, "alignment": "center", "size": 24.0, "delay": 0.04, "width": 700.0}}, {"id": 189, "prop": "subtitle", "attributes": {}}, {"id": 190, "prop": "Blocker", "attributes": {"a": 0.0, "r": 0.0, "g": 0.0, "b": 0.0, "fadetime": 0.5, "block": "true"}}, {"id": 191, "prop": "charslot", "attributes": {"slot": "m", "name": "avg_2027_wang_1#11$2"}}, {"id": 192, "prop": "name", "attributes": {"content": "In any case, you're not awake. You're still in the dream.", "name": "Wang"}, "figure_art": "avg_2027_wang_1#11$2"}, {"id": 193, "prop": "Dialog", "attributes": {}}, {"id": 194, "prop": "Blocker", "attributes": {"a": 0.6, "r": 0.0, "g": 0.0, "b": 0.0, "fadetime": 0.5, "block": "true"}}, {"id": 195, "prop": "Subtitle", "attributes": {"text": "Of course I'm awake... you had awakened me centuries ago, when you intruded upon my dream.", "x": 300.0, "y": 370.0, "alignment": "center", "size": 24.0, "delay": 0.04, "width": 700.0}}, {"id": 196, "prop": "subtitle", "attributes": {}}, {"id": 197, "prop": "Blocker", "attributes": {"a": 0.0, "r": 0.0, "g": 0.0, "b": 0.0, "fadetime": 0.5, "block": "true"}}, {"id": 198, "prop": "charslot", "attributes": {"slot": "m", "name": "avg_2027_wang_1#11$2"}}, {"id": 199, "prop": "name", "attributes": {"content": "You're bluffing... I would not be standing here, if you were truly awake.", "name": "Wang"}, "figure_art": "avg_2027_wang_1#11$2"}, {"id": 200, "prop": "name", "attributes": {"content": "You flexed in your dream and thought you had woken up.", "name": "Wang"}, "figure_art": "avg_2027_wang_1#11$2"}, {"id": 201, "prop": "name", "attributes": {"content": "You, a mere dreamwalker not yet awake, dare call yourself awake?", "name": "Wang"}, "figure_art": "avg_2027_wang_1#11$2"}, {"id": 202, "prop": "Dialog", "attributes": {}}, {"id": 203, "prop": "Blocker", "attributes": {"a": 0.6, "r": 0.0, "g": 0.0, "b": 0.0, "fadetime": 0.5, "block": "true"}}, {"id": 204, "prop": "Subtitle", "attributes": {"text": "Dreamwalker? Very well, we'll call this a journey in a dream.", "x": 300.0, "y": 370.0, "alignment": "center", "size": 24.0, "delay": 0.04, "width": 700.0}}, {"id": 205, "prop": "Subtitle", "attributes": {"text": "But I see those games you and your siblings play with those puny humans, and your foolish, flawed, presumptuous plan to replace me.", "x": 300.0, "y": 370.0, "alignment": "center", "size": 24.0, "delay": 0.04, "width": 700.0}}, {"id": 206, "prop": "Subtitle", "attributes": {"text": "You want to become the same as the humans, to become such fickle, puny creatures, in order to escape your fate?", "x": 300.0, "y": 370.0, "alignment": "center", "size": 24.0, "delay": 0.04, "width": 700.0}}, {"id": 207, "prop": "Subtitle", "attributes": {"text": "How pathetic... how laughable!", "x": 300.0, "y": 370.0, "alignment": "center", "size": 24.0, "delay": 0.04, "width": 700.0}}, {"id": 208, "prop": "subtitle", "attributes": {}}, {"id": 209, "prop": "Blocker", "attributes": {"a": 0.0, "r": 0.0, "g": 0.0, "b": 0.0, "fadetime": 0.5, "block": "true"}}, {"id": 210, "prop": "Dialog", "attributes": {}}, {"id": 211, "prop": "charslot", "attributes": {"slot": "m", "name": "avg_2027_wang_1#11$2"}}, {"id": 212, "prop": "name", "attributes": {"content": "You forget that these puny creatures defeated you and imprisoned you for a thousand years.", "name": "Wang"}, "figure_art": "avg_2027_wang_1#11$2"}, {"id": 213, "prop": "name", "attributes": {"content": "Does it matter if you're awake? You're a shadow, a reflection—a phantom questioning its own shade, a reflection in fleeting water...", "name": "Wang"}, "figure_art": "avg_2027_wang_1#11$2"}, {"id": 214, "prop": "name", "attributes": {"content": "Killing you will not be difficult.", "name": "Wang"}, "figure_art": "avg_2027_wang_1#11$2"}, {"id": 215, "prop": "Dialog", "attributes": {}}, {"id": 216, "prop": "Blocker", "attributes": {"a": 0.6, "r": 0.0, "g": 0.0, "b": 0.0, "fadetime": 0.5, "block": "true"}}, {"id": 217, "prop": "Subtitle", "attributes": {"text": "Is that so?", "x": 300.0, "y": 370.0, "alignment": "center", "size": 24.0, "delay": 0.04, "width": 700.0}}, {"id": 218, "prop": "subtitle", "attributes": {}}, {"id": 219, "prop": "charslot", "attributes": {"duration": 0.5}}, {"id": 220, "prop": "Blocker", "attributes": {"a": 0.0, "r": 0.0, "g": 0.0, "b": 0.0, "fadetime": 0.5, "block": "true"}}, {"id": 221, "prop": "playsound", "attributes": {"key": "$d_avg_heavyrockroll"}}, {"id": 222, "prop": "delay", "attributes": {"time": 0.5}}, {"id": 223, "prop": "CameraShake", "attributes": {"duration": 1.0, "xstrength": 3.0, "ystrength": 10.0, "vibrato": 25.0, "randomness": 90.0, "fadeout": "true", "block": "false"}}, {"id": 224, "prop": "delay", "attributes": {"time": 1.0}}, {"id": 225, "prop": "name", "attributes": {"content": "The proxy turns around to look at the corridor that he just walked through, but finds no path."}}, {"id": 226, "prop": "dialog", "attributes": {}}, {"id": 227, "prop": "Blocker", "attributes": {"a": 0.6, "r": 0.0, "g": 0.0, "b": 0.0, "fadetime": 0.5, "block": "true"}}, {"id": 228, "prop": "Subtitle", "attributes": {"text": "Why are you afraid, then?", "x": 300.0, "y": 370.0, "alignment": "center", "size": 24.0, "delay": 0.04, "width": 700.0}}, {"id": 229, "prop": "Subtitle", "attributes": {"text": "It took so long for you to get a chance to see me like this. If you are not afraid, why have you not torn me to pieces in your hatred?", "x": 300.0, "y": 370.0, "alignment": "center", "size": 24.0, "delay": 0.04, "width": 700.0}}, {"id": 230, "prop": "Subtitle", "attributes": {"text": "Pathetic... foolish.", "x": 300.0, "y": 370.0, "alignment": "center", "size": 24.0, "delay": 0.04, "width": 700.0}}, {"id": 231, "prop": "subtitle", "attributes": {}}, {"id": 232, "prop": "Blocker", "attributes": {"a": 0.0, "r": 0.0, "g": 0.0, "b": 0.0, "fadetime": 0.5, "block": "true"}}, {"id": 233, "prop": "charslot", "attributes": {"slot": "m", "name": "avg_2027_wang_1#11$2"}}, {"id": 234, "prop": "name", "attributes": {"content": "Watch your tongue.", "name": "Wang"}, "figure_art": "avg_2027_wang_1#11$2"}, {"id": 235, "prop": "Dialog", "attributes": {}}, {"id": 236, "prop": "Blocker", "attributes": {"a": 0.6, "r": 0.0, "g": 0.0, "b": 0.0, "fadetime": 0.5, "block": "true"}}, {"id": 237, "prop": "Subtitle", "attributes": {"text": "Hahahahahahaha!", "x": 300.0, "y": 370.0, "alignment": "center", "size": 24.0, "delay": 0.04, "width": 700.0}}, {"id": 238, "prop": "Subtitle", "attributes": {"text": "Didn't you want to fight me to the death?", "x": 300.0, "y": 370.0, "alignment": "center", "size": 24.0, "delay": 0.04, "width": 700.0}}, {"id": 239, "prop": "Subtitle", "attributes": {"text": "Then come. Do what you do best.", "x": 300.0, "y": 370.0, "alignment": "center", "size": 24.0, "delay": 0.04, "width": 700.0}}, {"id": 240, "prop": "subtitle", "attributes": {}}, {"id": 241, "prop": "Blocker", "attributes": {"a": 0.0, "r": 0.0, "g": 0.0, "b": 0.0, "fadetime": 0.5, "block": "true"}}, {"id": 242, "prop": "charslot", "attributes": {"slot": "m", "focus": "n"}}, {"id": 243, "prop": "name", "attributes": {"content": "A weiqi board appears in front of Wang, with a familiar crack on it."}}, {"id": 244, "prop": "name", "attributes": {"content": "Without asking, the mysterious foe takes the white stone and goes first according to tradition."}}, {"id": 245, "prop": "PlaySound", "attributes": {"key": "$d_avg_chess"}}, {"id": 246, "prop": "name", "attributes": {"content": "The first stone is placed in the Tianyuan position—the center of the board."}}, {"id": 247, "prop": "charslot", "attributes": {"slot": "m", "name": "avg_2027_wang_1#1$2"}}, {"id": 248, "prop": "name", "attributes": {"content": "First move, Tianyuan.", "name": "Wang"}, "figure_art": "avg_2027_wang_1#1$2"}, {"id": 249, "prop": "name", "attributes": {"content": "Are you mocking me?", "name": "Wang"}, "figure_art": "avg_2027_wang_1#1$2"}, {"id": 250, "prop": "Dialog", "attributes": {}}, {"id": 251, "prop": "Blocker", "attributes": {"a": 0.6, "r": 0.0, "g": 0.0, "b": 0.0, "fadetime": 0.5, "block": "true"}}, {"id": 252, "prop": "Subtitle", "attributes": {"text": "You'll find out when the game has ended. ", "x": 300.0, "y": 370.0, "alignment": "center", "size": 24.0, "delay": 0.04, "width": 700.0}}, {"id": 253, "prop": "Subtitle", "attributes": {"text": "Your turn.", "x": 300.0, "y": 370.0, "alignment": "center", "size": 24.0, "delay": 0.04, "width": 700.0}}, {"id": 254, "prop": "subtitle", "attributes": {}}, {"id": 255, "prop": "Blocker", "attributes": {"a": 0.0, "r": 0.0, "g": 0.0, "b": 0.0, "fadetime": 0.5, "block": "true"}}, {"id": 256, "prop": "charslot", "attributes": {"slot": "m", "name": "avg_2027_wang_1#12$2"}}, {"id": 257, "prop": "name", "attributes": {"content": "—!", "name": "Wang"}, "figure_art": "avg_2027_wang_1#12$2"}, {"id": 258, "prop": "PlaySound", "attributes": {"key": "$d_avg_chess", "delay": 1.0}}, {"id": 259, "prop": "charslot", "attributes": {"slot": "m", "focus": "n"}}, {"id": 260, "prop": "name", "attributes": {"content": "He takes a black piece. The nineteen-by-nineteen board is intimately familiar to him; he has not tasted defeat in a long, long time."}}, {"id": 261, "prop": "name", "attributes": {"content": "Yet it seems as though his opponent sees through his every move, every thought, every emotion."}}, {"id": 262, "prop": "name", "attributes": {"content": "He soon finds himself at a disadvantage, even though his opponent had forfeited the opening move."}}, {"id": 263, "prop": "charslot", "attributes": {"slot": "m", "name": "avg_2027_wang_1#6$2"}}, {"id": 264, "prop": "name", "attributes": {"content": "Impossible...", "name": "Wang"}, "figure_art": "avg_2027_wang_1#6$2"}, {"id": 265, "prop": "Dialog", "attributes": {}}, {"id": 266, "prop": "Blocker", "attributes": {"a": 0.6, "r": 0.0, "g": 0.0, "b": 0.0, "fadetime": 0.5, "block": "true"}}, {"id": 267, "prop": "Subtitle", "attributes": {"text": "Why would it be?", "x": 300.0, "y": 370.0, "alignment": "center", "size": 24.0, "delay": 0.04, "width": 700.0}}, {"id": 268, "prop": "Subtitle", "attributes": {"text": "Have you not realized that all the intricate moves that you have pondered, all your puny stratagems, are no secrets to me? ", "x": 300.0, "y": 370.0, "alignment": "center", "size": 24.0, "delay": 0.04, "width": 700.0}}, {"id": 269, "prop": "subtitle", "attributes": {}}, {"id": 270, "prop": "Blocker", "attributes": {"a": 0.0, "r": 0.0, "g": 0.0, "b": 0.0, "fadetime": 0.5, "block": "true"}}, {"id": 271, "prop": "charslot", "attributes": {}}, {"id": 272, "prop": "charslot", "attributes": {"slot": "m", "name": "avg_npc_2129_1#1$1", "duration": 1.5}}, {"id": 273, "prop": "delay", "attributes": {"time": 2.5}}, {"id": 274, "prop": "name", "attributes": {"content": "Because I am you.", "name": "Wang?"}, "figure_art": "avg_npc_2129_1#1$1"}, {"id": 275, "prop": "charslot", "attributes": {"slot": "m", "name": "avg_2027_wang_1#6$2"}}, {"id": 276, "prop": "name", "attributes": {"content": "—?!", "name": "Wang"}, "figure_art": "avg_2027_wang_1#6$2"}, {"id": 277, "prop": "charslot", "attributes": {"slot": "m", "name": "avg_npc_2129_1#9$1"}}, {"id": 278, "prop": "name", "attributes": {"content": "Giving up already? No, no, that won't do.", "name": "Wang?"}, "figure_art": "avg_npc_2129_1#9$1"}, {"id": 279, "prop": "name", "attributes": {"content": "You must finish the game.", "name": "Wang?"}, "figure_art": "avg_npc_2129_1#9$1"}, {"id": 280, "prop": "charslot", "attributes": {"slot": "m", "name": "avg_2027_wang_1#12$2"}}, {"id": 281, "prop": "name", "attributes": {"content": "So be it.", "name": "Wang"}, "figure_art": "avg_2027_wang_1#12$2"}, {"id": 282, "prop": "charslot", "attributes": {}}, {"id": 283, "prop": "name", "attributes": {"content": "He clenches his teeth and picks up another stone."}}, {"id": 284, "prop": "PlaySound", "attributes": {"key": "$d_avg_chess"}}, {"id": 285, "prop": "name", "attributes": {"content": "Every move causes a splitting headache. Every move drains his spirit."}}, {"id": 286, "prop": "name", "attributes": {"content": "The game is finally concluded after another hundred moves or so, with all endgame plays settled. Black wins by the slimmest of margins—half a point—as the points are tallied."}}, {"id": 287, "prop": "name", "attributes": {"content": "The player is exhausted, at his last gasp."}}, {"id": 288, "prop": "dialog", "attributes": {}}, {"id": 289, "prop": "charslot", "attributes": {"slot": "m", "name": "avg_2027_wang_1#5$2", "duration": 0.5, "afrom": 0.0, "ato": 0.7}}, {"id": 290, "prop": "delay", "attributes": {"time": 1.0}}, {"id": 291, "prop": "name", "attributes": {"content": "(Pants feebly)", "name": "Wang"}, "figure_art": "avg_2027_wang_1#5$2"}, {"id": 292, "prop": "charslot", "attributes": {"slot": "m", "name": "avg_2027_wang_1#3$2", "afrom": 0.7, "ato": 0.7}}, {"id": 293, "prop": "name", "attributes": {"content": "You lose.", "name": "Wang"}, "figure_art": "avg_2027_wang_1#3$2"}, {"id": 294, "prop": "name", "attributes": {"content": "Arrogant as ever...", "name": "Wang"}, "figure_art": "avg_2027_wang_1#3$2"}, {"id": 295, "prop": "dialog", "attributes": {}}, {"id": 296, "prop": "charslot", "attributes": {}}, {"id": 297, "prop": "PlaySound", "attributes": {"key": "$d_avg_hugemonsterroar", "volume": 0.7}}, {"id": 298, "prop": "CameraShake", "attributes": {"duration": 1.5, "xstrength": 15.0, "ystrength": 15.0, "vibrato": 35.0, "randomness": 90.0, "fadeout": "true", "block": "false"}}, {"id": 299, "prop": "delay", "attributes": {"time": 2.5}}, {"id": 300, "prop": "charslot", "attributes": {"slot": "m", "name": "avg_npc_2129_1#8$1"}}, {"id": 301, "prop": "name", "attributes": {"content": "Haha... hahahahaha!", "name": "Wang?"}, "figure_art": "avg_npc_2129_1#8$1"}, {"id": 302, "prop": "name", "attributes": {"content": "Leaving aside whether this child's play even counts... do you think this is the only game between us?", "name": "Wang?"}, "figure_art": "avg_npc_2129_1#8$1"}, {"id": 303, "prop": "charslot", "attributes": {"slot": "m", "name": "avg_2027_wang_1#11$2", "afrom": 0.7, "ato": 0.7}}, {"id": 304, "prop": "name", "attributes": {"content": "...?", "name": "Wang"}, "figure_art": "avg_2027_wang_1#11$2"}, {"id": 305, "prop": "charslot", "attributes": {"slot": "m", "name": "avg_npc_2129_1#9$1"}}, {"id": 306, "prop": "name", "attributes": {"content": "The name of this game is Wang. You may have won this round, but have you any idea how insignificant it is in the big picture?", "name": "Wang?"}, "figure_art": "avg_npc_2129_1#9$1"}, {"id": 307, "prop": "name", "attributes": {"content": "Step back. Go there and look back, and see if there is any meaning in these moves that took every last drop of your being.", "name": "Wang?"}, "figure_art": "avg_npc_2129_1#9$1"}, {"id": 308, "prop": "charslot", "attributes": {}}, {"id": 309, "prop": "name", "attributes": {"content": "Against his will, Wang gets up and takes a few steps back."}}, {"id": 310, "prop": "name", "attributes": {"content": "It is only a few steps, but the board that he has been seeing has shrunk to a tiny piece."}}, {"id": 311, "prop": "charslot", "attributes": {"slot": "m", "name": "avg_npc_2129_1#8$1"}}, {"id": 312, "prop": "name", "attributes": {"content": "No matter how you flail and struggle, it is no more than one-twelfth of the game.", "name": "Wang?"}, "figure_art": "avg_npc_2129_1#8$1"}, {"id": 313, "prop": "name", "attributes": {"content": "All the twists and turns of your black pieces have not determined the outcome of a single corner. Why do you think you can make me concede?", "name": "Wang?"}, "figure_art": "avg_npc_2129_1#8$1"}, {"id": 314, "prop": "charslot", "attributes": {}}, {"id": 315, "prop": "name", "attributes": {"content": "Wang forces himself to look..."}}, {"id": 316, "prop": "name", "attributes": {"content": "It is no longer a nineteen-by-nineteen board, but hundreds of lines vertical and across. The game that he had poured his heart and soul into just to win by a hair looks utterly insignificant on the vast board."}}, {"id": 317, "prop": "name", "attributes": {"content": "Countless white pieces, as many as there are stars in the sky, lie beyond the board, which itself seems endless. There is no room to intervene in their formation—as immutable as Sui's anger and contempt, which have simmered for a thousand years."}}, {"id": 318, "prop": "charslot", "attributes": {"slot": "m", "name": "avg_2027_wang_1#12$2", "afrom": 0.7, "ato": 0.7}}, {"id": 319, "prop": "name", "attributes": {"content": "You planned this...", "name": "Wang"}, "figure_art": "avg_2027_wang_1#12$2"}, {"id": 320, "prop": "charslot", "attributes": {"slot": "m", "name": "avg_npc_2129_1#7$1"}}, {"id": 321, "prop": "name", "attributes": {"content": "Of course I planned this.", "name": "Wang?"}, "figure_art": "avg_npc_2129_1#7$1"}, {"id": 322, "prop": "name", "attributes": {"content": "This plan began to take form in my countless dreams, ever since you glimpsed into my mind centuries ago.", "name": "Wang?"}, "figure_art": "avg_npc_2129_1#7$1"}, {"id": 323, "prop": "name", "attributes": {"content": "A White would begin to lay the pieces around you, quietly and unbeknownst to you.", "name": "Wang?"}, "figure_art": "avg_npc_2129_1#7$1"}, {"id": 324, "prop": "name", "attributes": {"content": "What you have done, he made a note of. What you did not finish, he finished for you. What you did not do, he did in your image.", "name": "Wang?"}, "figure_art": "avg_npc_2129_1#7$1"}, {"id": 325, "prop": "name", "attributes": {"content": "He made you wary of the humans, and the humans wary of you, forcing you and your kind to return here... this source of your immortality for centuries.", "name": "Wang?"}, "figure_art": "avg_npc_2129_1#7$1"}, {"id": 326, "prop": "charslot", "attributes": {"slot": "m", "name": "avg_2027_wang_1#11$2", "afrom": 0.7, "ato": 0.7}}, {"id": 327, "prop": "name", "attributes": {"content": "Why do you care that we live?", "name": "Wang"}, "figure_art": "avg_2027_wang_1#11$2"}, {"id": 328, "prop": "charslot", "attributes": {"slot": "m", "name": "avg_npc_2129_1#3$1"}}, {"id": 329, "prop": "name", "attributes": {"content": "As long as I live, you will always have a choice, the last thing that Yan wants to see—to return to my consciousness, and destroy everything that was built upon the Great Hunt.", "name": "Wang?"}, "figure_art": "avg_npc_2129_1#3$1"}, {"id": 330, "prop": "name", "attributes": {"content": "As long as you live, I will never regain my full strength, strength that will allow me to break my shackles.", "name": "Wang?"}, "figure_art": "avg_npc_2129_1#3$1"}, {"id": 331, "prop": "charslot", "attributes": {"slot": "m", "name": "avg_npc_2129_1#2$1"}}, {"id": 332, "prop": "name", "attributes": {"content": "Our lives are too intertwined for peace to be a possibility... yet you would seek peace with the humans?", "name": "Wang?"}, "figure_art": "avg_npc_2129_1#2$1"}, {"id": 333, "prop": "name", "attributes": {"content": "Yan would not abide me, who almost became their god. Why would they abide you when you replace me?", "name": "Wang?"}, "figure_art": "avg_npc_2129_1#2$1"}, {"id": 334, "prop": "charslot", "attributes": {"slot": "m", "name": "avg_npc_2129_1#10$1"}}, {"id": 335, "prop": "name", "attributes": {"content": "You are not worthy to play at this board... I will take your life, then the lives of your 'siblings'.", "name": "Wang?"}, "figure_art": "avg_npc_2129_1#10$1"}, {"id": 336, "prop": "name", "attributes": {"content": "Vanish, now, as your inevitable fate—", "name": "Wang?"}, "figure_art": "avg_npc_2129_1#10$1"}, {"id": 337, "prop": "dialog", "attributes": {}}, {"id": 338, "prop": "charslot", "attributes": {}}, {"id": 339, "prop": "CameraShake", "attributes": {"duration": 0.3, "xstrength": 30.0, "ystrength": 30.0, "vibrato": 35.0, "randomness": 90.0, "fadeout": "true", "block": "false"}}, {"id": 340, "prop": "PlaySound", "attributes": {"key": "$e_skill_skulsrsword", "volume": 0.9}}, {"id": 341, "prop": "Blocker", "attributes": {"a": 1.0, "r": 0.5, "g": 0.0, "b": 0.0, "fadetime": 0.3, "block": "true"}}, {"id": 342, "prop": "stopmusic", "attributes": {"fadetime": 2.0}}, {"id": 343, "prop": "Dialog", "attributes": {}}, {"id": 344, "prop": "Blocker", "attributes": {"a": 1.0, "r": 0.0, "g": 0.0, "b": 0.0, "fadetime": 2.0, "block": "true"}}, {"id": 345, "prop": "charslot", "attributes": {}}, {"id": 346, "prop": "delay", "attributes": {"time": 2.0}}, {"id": 347, "prop": "Background", "attributes": {"image": "70_g5_tjtopfloor", "screenadapt": "coverall"}}, {"id": 348, "prop": "Blocker", "attributes": {"a": 0.0, "r": 0.0, "g": 0.0, "b": 0.0, "fadetime": 2.0, "block": "true"}}, {"id": 349, "prop": "delay", "attributes": {"time": 1.0}}, {"id": 350, "prop": "playMusic", "attributes": {"intro": "$dignified_intro", "key": "$dignified_loop", "volume": 0.6}}, {"id": 351, "prop": "charslot", "attributes": {"slot": "m", "name": "avg_npc_2125_1#11$1", "duration": 1.0}}, {"id": 352, "prop": "delay", "attributes": {"time": 1.5}}, {"id": 353, "prop": "name", "attributes": {"content": "The True Lung let Wang go to the Tomb of Sui alone...", "name": "Jie"}, "figure_art": "avg_npc_2125_1#11$1"}, {"id": 354, "prop": "name", "attributes": {"content": "He would not have given Wang the opportunity to tell me...", "name": "Jie"}, "figure_art": "avg_npc_2125_1#11$1"}, {"id": 355, "prop": "charslot", "attributes": {"slot": "m", "name": "avg_npc_2127_1#4$2"}}, {"id": 356, "prop": "name", "attributes": {"content": "...", "name": "Chun"}, "figure_art": "avg_npc_2127_1#4$2"}, {"id": 357, "prop": "charslot", "attributes": {"slot": "m", "name": "avg_npc_2125_1#11$1"}}, {"id": 358, "prop": "name", "attributes": {"content": "He never wanted to hurt anyone.", "name": "Jie"}, "figure_art": "avg_npc_2125_1#11$1"}, {"id": 359, "prop": "name", "attributes": {"content": "Words were never his strong suit. He was obsessed with victory and defeat, but cared nothing for loss and gain... the shrewdest, and the most foolish amongst us.", "name": "Jie"}, "figure_art": "avg_npc_2125_1#11$1"}, {"id": 360, "prop": "name", "attributes": {"content": "He saw through every scheme and treachery, but he could not do something as simple as letting those around him truly know him.", "name": "Jie"}, "figure_art": "avg_npc_2125_1#11$1"}, {"id": 361, "prop": "charslot", "attributes": {"slot": "m", "name": "avg_npc_2125_1#10$1"}}, {"id": 362, "prop": "name", "attributes": {"content": "Besides... am I not the proxy that the Sui Regulator, and you, have always feared the most?", "name": "Jie"}, "figure_art": "avg_npc_2125_1#10$1"}, {"id": 363, "prop": "charslot", "attributes": {"slot": "m", "name": "avg_npc_2127_1#5$2"}}, {"id": 364, "prop": "name", "attributes": {"content": "...?!", "name": "Chun"}, "figure_art": "avg_npc_2127_1#5$2"}, {"id": 365, "prop": "charslot", "attributes": {"slot": "m", "name": "avg_npc_2125_1#11$1"}}, {"id": 366, "prop": "name", "attributes": {"content": "I knew. Or rather, I knew they would tell you.", "name": "Jie"}, "figure_art": "avg_npc_2125_1#11$1"}, {"id": 367, "prop": "charslot", "attributes": {"slot": "m", "name": "avg_npc_2125_1#4$1"}}, {"id": 368, "prop": "name", "attributes": {"content": "I can feel it, even if you didn't say anything...", "name": "Jie"}, "figure_art": "avg_npc_2125_1#4$1"}, {"id": 369, "prop": "name", "attributes": {"content": "I thought I could control this power in time. Lately, though, I'm feeling less and less like myself...", "name": "Jie"}, "figure_art": "avg_npc_2125_1#4$1"}, {"id": 370, "prop": "charslot", "attributes": {"slot": "m", "name": "avg_npc_2125_1#9$1"}}, {"id": 371, "prop": "name", "attributes": {"content": "My memories began to grow indistinct many years ago. In recent years, the same has happened to my emotions.", "name": "Jie"}, "figure_art": "avg_npc_2125_1#9$1"}, {"id": 372, "prop": "name", "attributes": {"content": "Perhaps...", "name": "Jie"}, "figure_art": "avg_npc_2125_1#9$1"}, {"id": 373, "prop": "dialog", "attributes": {}}, {"id": 374, "prop": "delay", "attributes": {"time": 1.5}}, {"id": 375, "prop": "charslot", "attributes": {"slot": "m", "name": "avg_npc_2125_1#11$1"}}, {"id": 376, "prop": "name", "attributes": {"content": "There's something I want to ask you, Chun, impolite as it may be.", "name": "Jie"}, "figure_art": "avg_npc_2125_1#11$1"}, {"id": 377, "prop": "name", "attributes": {"content": "What did you feel when your mother died?", "name": "Jie"}, "figure_art": "avg_npc_2125_1#11$1"}, {"id": 378, "prop": "charslot", "attributes": {"slot": "m", "name": "avg_npc_2127_1#13$2", "focus": "n"}}, {"id": 379, "prop": "name", "attributes": {"content": "Underneath her thick black hair, the Elf's ears twitched."}}, {"id": 380, "prop": "charslot", "attributes": {"slot": "m", "name": "avg_npc_2127_1#13$2"}}, {"id": 381, "prop": "name", "attributes": {"content": "Why do you ask?", "name": "Chun"}, "figure_art": "avg_npc_2127_1#13$2"}, {"id": 382, "prop": "charslot", "attributes": {"slot": "m", "name": "avg_npc_2125_1#10$1"}}, {"id": 383, "prop": "name", "attributes": {"content": "Because there is still hope for Wang.", "name": "Jie"}, "figure_art": "avg_npc_2125_1#10$1"}, {"id": 384, "prop": "charslot", "attributes": {"slot": "m", "name": "avg_npc_2127_1#5$2"}}, {"id": 385, "prop": "name", "attributes": {"content": "You're going to save him?!", "name": "Chun"}, "figure_art": "avg_npc_2127_1#5$2"}, {"id": 386, "prop": "charslot", "attributes": {"slot": "m", "name": "avg_npc_2125_1#10$1"}}, {"id": 387, "prop": "name", "attributes": {"content": "As it stands, with my strength and his, I can do no more than die in his place.", "name": "Jie"}, "figure_art": "avg_npc_2125_1#10$1"}, {"id": 388, "prop": "name", "attributes": {"content": "What is the death of a family member like, for beings like you and me?", "name": "Jie"}, "figure_art": "avg_npc_2125_1#10$1"}, {"id": 389, "prop": "charslot", "attributes": {"slot": "m", "name": "avg_npc_2127_1#10$2"}}, {"id": 390, "prop": "name", "attributes": {"content": "Why do you ask? Why do you have to open my wounds—", "name": "Chun"}, "figure_art": "avg_npc_2127_1#10$2"}, {"id": 391, "prop": "charslot", "attributes": {"slot": "m", "name": "avg_npc_2127_1#12$2"}}, {"id": 392, "prop": "dialog", "attributes": {}}, {"id": 393, "prop": "delay", "attributes": {"time": 1.0}}, {"id": 394, "prop": "charslot", "attributes": {"slot": "m", "focus": "n"}}, {"id": 395, "prop": "name", "attributes": {"content": "Suddenly, Chun understands."}}, {"id": 396, "prop": "name", "attributes": {"content": "Jie is asking for herself, and for Wang."}}, {"id": 397, "prop": "name", "attributes": {"content": "If losing a loved one is merely a little speck of sorrow in a long life, then she will choose death, and leave the insignificant sorrow to Wang, and become a loss that stings a little from time to time for her siblings."}}, {"id": 398, "prop": "name", "attributes": {"content": "If the pain of losing a loved one still threatens to tear one apart, even for those with lifespans far beyond the ordinary mortal, then she will choose to bear the unbearable pain, and the burden of those left behind, seeing the task of eliminating Sui through to the end."}}, {"id": 399, "prop": "name", "attributes": {"content": "An immortal being, facing the possibility of losing family forever for the first time."}}, {"id": 400, "prop": "name", "attributes": {"content": "Though she has written about meetings and partings innumerable times, finding no other measure to judge by, she can only rely on Chun to make a decision."}}, {"id": 401, "prop": "charslot", "attributes": {"slot": "m", "name": "avg_npc_2127_1#12$2"}}, {"id": 402, "prop": "name", "attributes": {"content": "...", "name": "Chun"}, "figure_art": "avg_npc_2127_1#12$2"}, {"id": 403, "prop": "charslot", "attributes": {"slot": "m", "focus": "n"}}, {"id": 404, "prop": "name", "attributes": {"content": "She only has to tell the truth."}}, {"id": 405, "prop": "name", "attributes": {"content": "That the pain of losing a loved one does not heal so easily, even after decades, after centuries."}}, {"id": 406, "prop": "name", "attributes": {"content": "That death is liberation and life is pain. Which way the scale tips is obvious."}}, {"id": 407, "prop": "name", "attributes": {"content": "That it was best for Wang to let him go, that Jie should remain and feel the pain that lingers. Wang reaps the death that he sowed while Jie remains. It is how things should be."}}, {"id": 408, "prop": "name", "attributes": {"content": "That Jie would cautiously advance the cause of eliminating Sui, without crossing the line as Wang did, incurring the wrath of the True Lung when the Sui Regulator received an anonymous tip."}}, {"id": 409, "prop": "name", "attributes": {"content": "But—"}}, {"id": 410, "prop": "dialog", "attributes": {}}, {"id": 411, "prop": "Blocker", "attributes": {"a": 1.0, "r": 0.0, "g": 0.0, "b": 0.0, "fadetime": 1.5, "block": "true"}}, {"id": 412, "prop": "charslot", "attributes": {}}, {"id": 413, "prop": "CameraEffect", "attributes": {"effect": "Grayscale", "fadetime": 0.0, "keep": "true", "initamount": 0.0, "amount": 0.7, "block": "true"}}, {"id": 414, "prop": "Background", "attributes": {"image": "70_g4_tjdiscussionroom", "screenadapt": "coverall"}}, {"id": 415, "prop": "Blocker", "attributes": {"a": 0.0, "r": 0.0, "g": 0.0, "b": 0.0, "fadetime": 1.5, "block": "true"}}, {"id": 416, "prop": "name", "attributes": {"content": "Eliminate the great evil, before dealing with the culprit.'"}}, {"id": 417, "prop": "name", "attributes": {"content": "There is no one in the Sky Mirror Pavilion or the Imperial Historical Cabinet who can stop her. It's becoming a real problem.'"}}, {"id": 418, "prop": "name", "attributes": {"content": "She should be held responsible if the history of Yan falls into chaos!'"}}, {"id": 419, "prop": "name", "attributes": {"content": "Imperial Historical Cabinet abolished. Takes control of the written language of Yan. No one may oppose her.'"}}, {"id": 420, "prop": "name", "attributes": {"content": "Reviews the livelihood of every household in the land. Anyone who has committed fraudulent acts has their name erased and is exiled to the borders. Thousands die.'"}}, {"id": 421, "prop": "dialog", "attributes": {}}, {"id": 422, "prop": "Blocker", "attributes": {"a": 1.0, "r": 0.0, "g": 0.0, "b": 0.0, "fadetime": 1.5, "block": "true"}}, {"id": 423, "prop": "charslot", "attributes": {}}, {"id": 424, "prop": "CameraEffect", "attributes": {"effect": "Grayscale", "fadetime": 0.0, "amount": 0.0, "block": "true"}}, {"id": 425, "prop": "charslot", "attributes": {"slot": "m", "name": "avg_npc_2127_1#12$2", "focus": "n"}}, {"id": 426, "prop": "Background", "attributes": {"image": "70_g5_tjtopfloor", "screenadapt": "coverall"}}, {"id": 427, "prop": "Blocker", "attributes": {"a": 0.0, "r": 0.0, "g": 0.0, "b": 0.0, "fadetime": 1.5, "block": "true"}}, {"id": 428, "prop": "name", "attributes": {"content": "Chaotic, murky memories grip the Candleholder's heart."}}, {"id": 429, "prop": "name", "attributes": {"content": "It is not right. She seems to remember that none of the speakers had faces."}}, {"id": 430, "prop": "name", "attributes": {"content": "Something is not right. It is false, fabricated, designed to drive a rift between Candleholder and proxy, turn them against each other."}}, {"id": 431, "prop": "name", "attributes": {"content": "But... is it not a fact that Jie's power is growing?"}}, {"id": 432, "prop": "name", "attributes": {"content": "She will become more powerful, more terrible, than the Sui beast itself. She cannot help it. I must help her. I must do my duty to Great Yan—"}}, {"id": 433, "prop": "name", "attributes": {"content": "Two entwined wills surge in her chest. One belongs to her, the other to those faceless people, but also..."}}, {"id": 434, "prop": "name", "attributes": {"content": "...To a Yan that does not want to give a proxy complete control over history."}}, {"id": 435, "prop": "name", "attributes": {"content": "She cannot help but suspect that her recruitment by the Sui Regulator was not luck, but planned."}}, {"id": 436, "prop": "name", "attributes": {"content": "She was assigned to watch the most difficult proxy to control, because of her long lifespan."}}, {"id": 437, "prop": "name", "attributes": {"content": "She would understand the monster that Jie would become, because of her interest in history."}}, {"id": 438, "prop": "name", "attributes": {"content": "She would lose her hard-earned home if she betrayed Great Yan, because she has nowhere to go."}}, {"id": 439, "prop": "name", "attributes": {"content": "Is that why?"}}, {"id": 440, "prop": "name", "attributes": {"content": "She feels the crushing weight of her burden. A rumbling sound fills her mind, and she cannot think."}}, {"id": 441, "prop": "name", "attributes": {"content": "She must do her duty to Yan, do her duty as Candleholder. By chance, she has seen Jie at her most fragile. She must let the great evil take the culprit's place."}}, {"id": 442, "prop": "name", "attributes": {"content": "It would be best for the proxies, even. Yan would lose a reason to wage war on them—"}}, {"id": 443, "prop": "charslot", "attributes": {"slot": "m", "name": "avg_npc_2127_1#13$2"}}, {"id": 444, "prop": "name", "attributes": {"content": "My mother...", "name": "Chun"}, "figure_art": "avg_npc_2127_1#13$2"}, {"id": 445, "prop": "name", "attributes": {"content": "When she passed... I felt...", "name": "Chun"}, "figure_art": "avg_npc_2127_1#13$2"}, {"id": 446, "prop": "charslot", "attributes": {"slot": "l", "name": "avg_npc_2127_1#1$2", "posfrom": "200,0", "posto": "200,0"}}, {"id": 447, "prop": "charslot", "attributes": {"slot": "m", "name": "avg_npc_2127_1#1$2"}}, {"id": 448, "prop": "name", "attributes": {"content": "I felt... very little.", "name": "Chun"}, "figure_art": "avg_npc_2127_1#13$2"}, {"id": 449, "prop": "dialog", "attributes": {}}, {"id": 450, "prop": "delay", "attributes": {"time": 0.5}}, {"id": 451, "prop": "charslot", "attributes": {"slot": "m", "name": "avg_npc_2127_1#12$2", "duration": 1.0, "focus": "all"}}, {"id": 452, "prop": "delay", "attributes": {"time": 1.0}}, {"id": 453, "prop": "name", "attributes": {"content": "<color=#d41f1f>The pain tore you apart.</color>"}}, {"id": 454, "prop": "charslot", "attributes": {"slot": "m", "name": "avg_npc_2127_1#1$2"}}, {"id": 455, "prop": "name", "attributes": {"content": "I felt as though the death of my mother left a hole in my heart, made me find something new to fill it.", "name": "Chun"}, "figure_art": "avg_npc_2127_1#1$2"}, {"id": 456, "prop": "dialog", "attributes": {}}, {"id": 457, "prop": "delay", "attributes": {"time": 0.5}}, {"id": 458, "prop": "charslot", "attributes": {"slot": "m", "name": "avg_npc_2127_1#7$2", "duration": 0.5, "focus": "all"}}, {"id": 459, "prop": "delay", "attributes": {"time": 1.0}}, {"id": 460, "prop": "name", "attributes": {"content": "<color=#d41f1f>It was as though your heart was ripped out from your chest, leaving behind a bloody hole, and you know that nothing would ever fill it, that things would never be the same again.</color>"}}, {"id": 461, "prop": "charslot", "attributes": {"slot": "m", "name": "avg_npc_2127_1#1$2"}}, {"id": 462, "prop": "name", "attributes": {"content": "I cried when I buried her, but... that was it. I stopped crying very soon.", "name": "Chun"}, "figure_art": "avg_npc_2127_1#1$2"}, {"id": 463, "prop": "dialog", "attributes": {}}, {"id": 464, "prop": "delay", "attributes": {"time": 0.5}}, {"id": 465, "prop": "charslot", "attributes": {"slot": "m", "name": "avg_npc_2127_1#13$2", "duration": 0.5, "focus": "all"}}, {"id": 466, "prop": "delay", "attributes": {"time": 1.0}}, {"id": 467, "prop": "name", "attributes": {"content": "<color=#d41f1f>You had cried your tears dry by the time the last dirt was laid over your mother's face, but still you could not stop crying. You had no idea what to do.</color>"}}, {"id": 468, "prop": "charslot", "attributes": {"slot": "m", "name": "avg_npc_2127_1#5$2"}}, {"id": 469, "prop": "name", "attributes": {"content": "Our... our journey is a long one. We'll find new things and meet new people; that will soothe the temporary pain.", "name": "Chun"}, "figure_art": "avg_npc_2127_1#5$2"}, {"id": 470, "prop": "dialog", "attributes": {}}, {"id": 471, "prop": "delay", "attributes": {"time": 0.5}}, {"id": 472, "prop": "charslot", "attributes": {"slot": "m", "name": "avg_npc_2127_1#7$2", "duration": 0.5, "focus": "all"}}, {"id": 473, "prop": "delay", "attributes": {"time": 1.0}}, {"id": 474, "prop": "name", "attributes": {"content": "<color=#d41f1f>Your life is too long, and the lasting things too few. When you lose them, they leave behind voids that can never be filled, wounds that never heal.</color>"}}, {"id": 475, "prop": "charslot", "attributes": {"slot": "m", "name": "avg_npc_2127_1#2$2"}}, {"id": 476, "prop": "name", "attributes": {"content": "I hardly even think of my mother anymore, because I have... you... I have... other friends.", "name": "Chun"}, "figure_art": "avg_npc_2127_1#2$2"}, {"id": 477, "prop": "dialog", "attributes": {}}, {"id": 478, "prop": "delay", "attributes": {"time": 0.5}}, {"id": 479, "prop": "charslot", "attributes": {"slot": "m", "name": "avg_npc_2127_1#12$2", "duration": 0.5, "focus": "all"}}, {"id": 480, "prop": "delay", "attributes": {"time": 1.0}}, {"id": 481, "prop": "name", "attributes": {"content": "<color=#d41f1f>Your loved ones appear in your dreams. They come to you when you are alone.</color>"}}, {"id": 482, "prop": "name", "attributes": {"content": "<color=#d41f1f>The pain grips your heart when you hear songs like the melodies that she once hummed. There is nowhere to run.</color>"}}, {"id": 483, "prop": "name", "attributes": {"content": "When I'm with you... I'm...", "name": "Chun"}}, {"id": 484, "prop": "charslot", "attributes": {"slot": "m", "name": "avg_npc_2127_1#13$2"}}, {"id": 485, "prop": "name", "attributes": {"content": "...I'm happy.", "name": "Chun"}, "figure_art": "avg_npc_2127_1#13$2"}, {"id": 486, "prop": "charslot", "attributes": {"duration": 1.0}}, {"id": 487, "prop": "name", "attributes": {"content": "She barely managed to utter those last few words, so great was her urge to throw up. She could hardly breathe."}}, {"id": 488, "prop": "name", "attributes": {"content": "She dares not look into the proxy's eyes."}}, {"id": 489, "prop": "name", "attributes": {"content": "She fears that the one before her would be blinded by her words and truly believe that loss is something that can be soothed by time."}}, {"id": 490, "prop": "name", "attributes": {"content": "She fears that the one before her would see through her lies, see her vile intention and despise her."}}, {"id": 491, "prop": "name", "attributes": {"content": "...She fears herself, for saying those words."}}, {"id": 492, "prop": "dialog", "attributes": {}}, {"id": 493, "prop": "charslot", "attributes": {"slot": "m", "name": "avg_npc_2125_1#11$1", "duration": 0.5}}, {"id": 494, "prop": "delay", "attributes": {"time": 1.0}}, {"id": 495, "prop": "name", "attributes": {"content": "I see...", "name": "Jie"}, "figure_art": "avg_npc_2125_1#11$1"}, {"id": 496, "prop": "charslot", "attributes": {"slot": "m", "name": "avg_npc_2125_1#1$1"}}, {"id": 497, "prop": "name", "attributes": {"content": "I see. Thank you.", "name": "Jie"}, "figure_art": "avg_npc_2125_1#1$1"}, {"id": 498, "prop": "name", "attributes": {"content": "You're a good Candleholder.", "name": "Jie"}, "figure_art": "avg_npc_2125_1#1$1"}, {"id": 499, "prop": "charslot", "attributes": {"slot": "m", "name": "avg_npc_2127_1#5$2"}}, {"id": 500, "prop": "name", "attributes": {"content": "?!", "name": "Chun"}, "figure_art": "avg_npc_2127_1#5$2"}, {"id": 501, "prop": "charslot", "attributes": {"slot": "m", "focus": "n"}}, {"id": 502, "prop": "name", "attributes": {"content": "The murk in the Candleholder's chest suddenly clears. There is only an empty hole there now."}}, {"id": 503, "prop": "name", "attributes": {"content": "Wind blows through the hole and speaks in her voice."}}, {"id": 504, "prop": "charslot", "attributes": {"slot": "m", "name": "avg_npc_2127_1#13$2"}}, {"id": 505, "prop": "name", "attributes": {"content": "Jie, I...", "name": "Chun"}, "figure_art": "avg_npc_2127_1#13$2"}, {"id": 506, "prop": "charslot", "attributes": {"slot": "m", "name": "avg_npc_2125_1#7$1"}}, {"id": 507, "prop": "name", "attributes": {"content": "It was a cruel question. But I asked because my heart was in turmoil.", "name": "Jie"}, "figure_art": "avg_npc_2125_1#7$1"}, {"id": 508, "prop": "charslot", "attributes": {"slot": "m", "name": "avg_npc_2125_1#4$1"}}, {"id": 509, "prop": "name", "attributes": {"content": "On second thought, I would likely have made the same decision, whether I asked the question or not. I regretted it as soon as I asked.", "name": "Jie"}, "figure_art": "avg_npc_2125_1#4$1"}, {"id": 510, "prop": "name", "attributes": {"content": "You're smart. You would have realized that I was forcing my Candleholder to choose my death or Wang's.", "name": "Jie"}, "figure_art": "avg_npc_2125_1#4$1"}, {"id": 511, "prop": "charslot", "attributes": {"slot": "m", "name": "avg_npc_2125_1#11$1"}}, {"id": 512, "prop": "name", "attributes": {"content": "I shouldn't have made you do this.", "name": "Jie"}, "figure_art": "avg_npc_2125_1#11$1"}, {"id": 513, "prop": "name", "attributes": {"content": "You didn't say anything about yourself. You chose to communicate Great Yan's will to me, that's all.", "name": "Jie"}, "figure_art": "avg_npc_2125_1#11$1"}, {"id": 514, "prop": "charslot", "attributes": {"slot": "m", "name": "avg_npc_2127_1#12$2"}}, {"id": 515, "prop": "name", "attributes": {"content": "...", "name": "Chun"}, "figure_art": "avg_npc_2127_1#12$2"}, {"id": 516, "prop": "charslot", "attributes": {"slot": "m", "name": "avg_npc_2125_1#9$1"}}, {"id": 517, "prop": "name", "attributes": {"content": "Death is an adventure that is unique for everyone. There is no previous experience to draw from. We must each walk our own path.", "name": "Jie"}, "figure_art": "avg_npc_2125_1#9$1"}, {"id": 518, "prop": "charslot", "attributes": {"slot": "m", "name": "avg_npc_2125_1#1$1"}}, {"id": 519, "prop": "name", "attributes": {"content": "The local annals that needed to be edited are on my desk. Take them to the Sui Regulator, when you have time.", "name": "Jie"}, "figure_art": "avg_npc_2125_1#1$1"}, {"id": 520, "prop": "charslot", "attributes": {"slot": "m", "name": "avg_npc_2127_1#13$2"}}, {"id": 521, "prop": "name", "attributes": {"content": "...Jie!", "name": "Chun"}, "figure_art": "avg_npc_2127_1#13$2"}, {"id": 522, "prop": "charslot", "attributes": {"slot": "m", "focus": "n"}}, {"id": 523, "prop": "name", "attributes": {"content": "Chun fights back her tears. Even crying would be a lie, here and now."}}, {"id": 524, "prop": "name", "attributes": {"content": "But the hole in her chest continues to sob, a sound that only she can hear. Finally, she forces a few sorrowful, powerless words from her chest."}}, {"id": 525, "prop": "charslot", "attributes": {"slot": "m", "name": "avg_npc_2127_1#13$2"}}, {"id": 526, "prop": "name", "attributes": {"content": "I... I'll be going.", "name": "Chun"}, "figure_art": "avg_npc_2127_1#13$2"}, {"id": 527, "prop": "charslot", "attributes": {"slot": "m", "name": "avg_npc_2125_1#7$1"}}, {"id": 528, "prop": "name", "attributes": {"content": "You...", "name": "Jie"}, "figure_art": "avg_npc_2125_1#7$1"}, {"id": 529, "prop": "charslot", "attributes": {"slot": "m", "name": "avg_npc_2125_1#9$1"}}, {"id": 530, "prop": "name", "attributes": {"content": "...Take care.", "name": "Jie"}, "figure_art": "avg_npc_2125_1#9$1"}, {"id": 531, "prop": "dialog", "attributes": {}}, {"id": 532, "prop": "charslot", "attributes": {"slot": "m", "name": "avg_npc_2127_1#13$2"}}, {"id": 533, "prop": "delay", "attributes": {"time": 0.5}}, {"id": 534, "prop": "PlaySound", "attributes": {"key": "$doorclosequite"}}, {"id": 535, "prop": "charslot", "attributes": {"duration": 1.5}}, {"id": 536, "prop": "delay", "attributes": {"time": 2.5}}, {"id": 537, "prop": "stopmusic", "attributes": {"fadetime": 3.0}}, {"id": 538, "prop": "Dialog", "attributes": {}}, {"id": 539, "prop": "Blocker", "attributes": {"a": 1.0, "r": 0.0, "g": 0.0, "b": 0.0, "fadetime": 3.0, "block": "true"}}, {"id": 540, "prop": "charslot", "attributes": {}}, {"id": 541, "prop": "delay", "attributes": {"time": 1.0}}, {"id": 542, "prop": "charslot", "attributes": {"slot": "left", "name": "avg_npc_2126_1#1$1"}}, {"id": 543, "prop": "charslot", "attributes": {"slot": "right", "name": "avg_npc_2125_1#10$1"}}, {"id": 544, "prop": "Background", "attributes": {"image": "70_g5_tjtopfloor", "screenadapt": "coverall"}}, {"id": 545, "prop": "Blocker", "attributes": {"a": 0.0, "r": 0.0, "g": 0.0, "b": 0.0, "fadetime": 2.0, "block": "true"}}, {"id": 546, "prop": "playMusic", "attributes": {"key": "$suilaststrick_loop", "volume": 0.6}}, {"id": 547, "prop": "delay", "attributes": {"time": 1.0}}, {"id": 548, "prop": "charslot", "attributes": {"slot": "left", "name": "avg_npc_2126_1#2$1", "focus": "l"}}, {"id": 549, "prop": "name", "attributes": {"content": "What's going on, Jie? The Imperial Guard is coming to the Sky Mirror Pavilion, and I almost got shut inside my own home by my Candleholder—", "name": "Jun"}}, {"id": 550, "prop": "charslot", "attributes": {"slot": "right", "name": "avg_npc_2125_1#10$1", "focus": "r"}}, {"id": 551, "prop": "name", "attributes": {"content": "...", "name": "Jie"}}, {"id": 552, "prop": "charslot", "attributes": {"slot": "left", "name": "avg_npc_2126_1#19$1", "focus": "l"}}, {"id": 553, "prop": "name", "attributes": {"content": "...Did something happen to Wang?", "name": "Jun"}}, {"id": 554, "prop": "charslot", "attributes": {"slot": "right", "name": "avg_npc_2125_1#11$1", "focus": "r"}}, {"id": 555, "prop": "name", "attributes": {"content": "You can hear it, can't you?", "name": "Jie"}}, {"id": 556, "prop": "name", "attributes": {"content": "Its... heartbeat.", "name": "Jie"}}, {"id": 557, "prop": "dialog", "attributes": {}}, {"id": 558, "prop": "charslot", "attributes": {"slot": "right", "focus": "n"}}, {"id": 559, "prop": "PlaySound", "attributes": {"key": "$d_gen_heartbeat", "volume": 1.0, "channel": "HB", "loop": "true"}}, {"id": 560, "prop": "stopsound", "attributes": {"channel": "HB", "fadetime": 1.0}}, {"id": 561, "prop": "delay", "attributes": {"time": 1.5}}, {"id": 562, "prop": "CameraShake", "attributes": {"duration": 0.3, "xstrength": 30.0, "ystrength": 30.0, "vibrato": 30.0, "randomness": 90.0, "fadeout": "true", "block": "false"}}, {"id": 563, "prop": "charslot", "attributes": {"slot": "left", "name": "avg_npc_2126_1#11$1", "focus": "l"}}, {"id": 564, "prop": "name", "attributes": {"content": "He went into the Tomb of Sui?!", "name": "Jun"}}, {"id": 565, "prop": "name", "attributes": {"content": "When?", "name": "Jun"}}, {"id": 566, "prop": "charslot", "attributes": {"slot": "right", "name": "avg_npc_2125_1#10$1", "focus": "r"}}, {"id": 567, "prop": "name", "attributes": {"content": "Two hours ago.", "name": "Jie"}}, {"id": 568, "prop": "charslot", "attributes": {"slot": "left", "name": "avg_npc_2126_1#12$1", "focus": "l"}}, {"id": 569, "prop": "name", "attributes": {"content": "We can talk about the rule-breaking later. The court clearly wants to exclude us, and time is short. What's your plan?", "name": "Jun"}}, {"id": 570, "prop": "charslot", "attributes": {"slot": "right", "name": "avg_npc_2125_1#10$1", "focus": "r"}}, {"id": 571, "prop": "name", "attributes": {"content": "I'm going to help Wang.", "name": "Jie"}}, {"id": 572, "prop": "charslot", "attributes": {"slot": "left", "name": "avg_npc_2126_1#17$1", "focus": "l"}}, {"id": 573, "prop": "name", "attributes": {"content": "I'll go with you.", "name": "Jun"}}, {"id": 574, "prop": "charslot", "attributes": {"slot": "right", "name": "avg_npc_2125_1#10$1", "focus": "r"}}, {"id": 575, "prop": "name", "attributes": {"content": "No.", "name": "Jie"}}, {"id": 576, "prop": "charslot", "attributes": {"slot": "left", "name": "avg_npc_2126_1#17$1", "focus": "l"}}, {"id": 577, "prop": "name", "attributes": {"content": "Why?", "name": "Jun"}}, {"id": 578, "prop": "charslot", "attributes": {"slot": "right", "name": "avg_npc_2125_1#10$1", "focus": "r"}}, {"id": 579, "prop": "name", "attributes": {"content": "He and I will take care of this.", "name": "Jie"}}, {"id": 580, "prop": "charslot", "attributes": {"slot": "left", "name": "avg_npc_2126_1#19$1", "focus": "l"}}, {"id": 581, "prop": "name", "attributes": {"content": "Are you sure?", "name": "Jun"}}, {"id": 582, "prop": "charslot", "attributes": {"slot": "right", "name": "avg_npc_2125_1#10$1", "focus": "r"}}, {"id": 583, "prop": "name", "attributes": {"content": "I'm sure.", "name": "Jie"}}, {"id": 584, "prop": "name", "attributes": {"content": "He and I have been making plans to eliminate Sui. There is no time to explain the plan right now.", "name": "Jie"}}, {"id": 585, "prop": "name", "attributes": {"content": "Your presence will not help; it will only increase the risk.", "name": "Jie"}}, {"id": 586, "prop": "name", "attributes": {"content": "Besides, there's something that I must ask you to do.", "name": "Jie"}}, {"id": 587, "prop": "Dialog", "attributes": {}}, {"id": 588, "prop": "Blocker", "attributes": {"a": 1.0, "r": 0.0, "g": 0.0, "b": 0.0, "fadetime": 2.0, "block": "true"}}, {"id": 589, "prop": "charslot", "attributes": {}}, {"id": 590, "prop": "Background", "attributes": {}}, {"id": 591, "prop": "delay", "attributes": {"time": 2.0}}, {"id": 592, "prop": "curtain", "attributes": {"direction": 0.0, "fillfrom": 0.1, "fillto": 0.2, "fadetime": 0.1}}, {"id": 593, "prop": "curtain", "attributes": {"direction": 4.0, "fillfrom": 0.1, "fillto": 0.2, "fadetime": 0.1}}, {"id": 594, "prop": "delay", "attributes": {"time": 0.1}}, {"id": 595, "prop": "Image", "attributes": {"image": "70_i03_2", "xScale": 1.05, "yScale": 1.05, "screenadapt": "coverall", "fadetime": 0.0, "y": 30.0}}, {"id": 596, "prop": "ImageTween", "attributes": {"yTo": 0.0, "duration": 2.0}}, {"id": 597, "prop": "Blocker", "attributes": {"a": 0.0, "r": 0.0, "g": 0.0, "b": 0.0, "fadetime": 2.0, "block": "true"}}, {"id": 598, "prop": "delay", "attributes": {"time": 1.0}}, {"id": 599, "prop": "curtain", "attributes": {"direction": 0.0, "fillfrom": 0.2, "fillto": 0.0, "fadetime": 1.5}}, {"id": 600, "prop": "curtain", "attributes": {"direction": 4.0, "fillfrom": 0.2, "fillto": 0.0, "fadetime": 1.5}}, {"id": 601, "prop": "delay", "attributes": {"time": 2.5}}, {"id": 602, "prop": "name", "attributes": {"content": "Take care of this writing knife.", "name": "Jie"}}, {"id": 603, "prop": "name", "attributes": {"content": "Your powers should be able to preserve it.", "name": "Jie"}}, {"id": 604, "prop": "name", "attributes": {"content": "What are you planning? How bad have things gotten?", "name": "Jun"}}, {"id": 605, "prop": "name", "attributes": {"content": "It will not awaken, not yet. I can promise you this. And so can Wang.", "name": "Jie"}}, {"id": 606, "prop": "name", "attributes": {"content": "But you...", "name": "Jun"}}, {"id": 607, "prop": "name", "attributes": {"content": "...Someone will come back.", "name": "Jie"}}, {"id": 608, "prop": "name", "attributes": {"content": "Either you or him?", "name": "Jun"}}, {"id": 609, "prop": "name", "attributes": {"content": "...", "name": "Jie"}}, {"id": 610, "prop": "name", "attributes": {"content": "I'm coming with you.", "name": "Jun"}}, {"id": 611, "prop": "name", "attributes": {"content": "No, Jun.", "name": "Jie"}}, {"id": 612, "prop": "name", "attributes": {"content": "I truly mean no offense. I need to entrust this writing knife to the keeping of someone who is absolutely just and impartial.", "name": "Jie"}}, {"id": 613, "prop": "name", "attributes": {"content": "If someone with ill intent gets their hands on it... it will do far more damage than the death of a single proxy.", "name": "Jie"}}, {"id": 614, "prop": "name", "attributes": {"content": "I thought about destroying it. In the end, I felt that it was worth preserving.", "name": "Jie"}}, {"id": 615, "prop": "name", "attributes": {"content": "The wrongs of the past should be righted, though I do not know at what price... perhaps the writing knife will be of help to you, or to Yan.", "name": "Jie"}}, {"id": 616, "prop": "name", "attributes": {"content": "Until the day comes when no one can use it anymore.", "name": "Jie"}}, {"id": 617, "prop": "dialog", "attributes": {}}, {"id": 618, "prop": "Image", "attributes": {"image": "70_i03_1", "xScale": 1.05, "yScale": 1.05, "screenadapt": "coverall", "fadetime": 1.0}}, {"id": 619, "prop": "delay", "attributes": {"time": 1.0}}, {"id": 620, "prop": "PlaySound", "attributes": {"key": "$d_avg_randrpfce"}}, {"id": 621, "prop": "cgitem", "attributes": {"image": "cgitem_70_i03_2", "style": "cg", "layer": 1.0, "afrom": 0.0, "ato": 1.0, "aduration": 0.5, "pfrom": "0,0", "pto": "0,-20", "sfrom": 1.2, "sto": 1.0, "sduration": 0.5}}, {"id": 622, "prop": "delay", "attributes": {"time": 0.2}}, {"id": 623, "prop": "PlaySound", "attributes": {"key": "$d_avg_randrpfce", "channel": "2", "volume": 0.6}}, {"id": 624, "prop": "cgitem", "attributes": {"image": "cgitem_70_i03_1", "style": "cg", "layer": 1.0, "afrom": 0.0, "ato": 1.0, "aduration": 0.5, "pfrom": "-350,0", "pto": "-350,-20", "sfrom": 1.2, "sto": 1.0, "sduration": 0.5}}, {"id": 625, "prop": "delay", "attributes": {"time": 0.2}}, {"id": 626, "prop": "cgitem", "attributes": {"image": "cgitem_70_i03_3", "style": "cg", "layer": 1.0, "afrom": 0.0, "ato": 1.0, "aduration": 0.5, "pfrom": "100,50", "pto": "100,30", "sfrom": 1.1, "sto": 1.0, "sduration": 0.5}}, {"id": 627, "prop": "delay", "attributes": {"time": 1.0}}, {"id": 628, "prop": "name", "attributes": {"content": "...", "name": "Jun"}}, {"id": 629, "prop": "name", "attributes": {"content": "Don't be like this, Jun.", "name": "Jie"}}, {"id": 630, "prop": "name", "attributes": {"content": "Maybe I'll come back with Wang.", "name": "Jie"}}, {"id": 631, "prop": "name", "attributes": {"content": "Then we'll go together to eat at Yu's, and listen to you sing...", "name": "Jie"}}, {"id": 632, "prop": "name", "attributes": {"content": "And if I never return...", "name": "Jie"}}, {"id": 633, "prop": "name", "attributes": {"content": "There's a long road ahead of you...", "name": "Jie"}}, {"id": 634, "prop": "Dialog", "attributes": {}}, {"id": 635, "prop": "Blocker", "attributes": {"a": 1.0, "r": 0.0, "g": 0.0, "b": 0.0, "fadetime": 3.0, "block": "true"}}, {"id": 636, "prop": "charslot", "attributes": {}}, {"id": 637, "prop": "hidecgitem", "attributes": {}}, {"id": 638, "prop": "delay", "attributes": {"time": 1.0}}, {"id": 639, "prop": "bgeffect", "attributes": {"name": "$eb_tyndall", "layer": 1.0}}, {"id": 640, "prop": "Image", "attributes": {"image": "70_i18", "xScale": 1.0, "yScale": 1.0, "screenadapt": "coverall"}}, {"id": 641, "prop": "ImageTween", "attributes": {"xScaleFrom": 1.0, "yScaleFrom": 1.0, "xScaleTo": 1.3, "yScaleTo": 1.3, "duration": 60.0, "block": "false"}}, {"id": 642, "prop": "Blocker", "attributes": {"a": 0.0, "r": 0.0, "g": 0.0, "b": 0.0, "fadetime": 3.0, "block": "true"}}, {"id": 643, "prop": "delay", "attributes": {"time": 1.0}}, {"id": 644, "prop": "name", "attributes": {"content": "...", "name": "Jie"}}, {"id": 645, "prop": "dialog", "attributes": {}}, {"id": 646, "prop": "delay", "attributes": {"time": 1.5}}, {"id": 647, "prop": "name", "attributes": {"content": "It is not so easy to not look back."}}, {"id": 648, "prop": "name", "attributes": {"content": "She looks at the innumerable lives and deaths recorded upon the shelves, many of which she had written with her own pen."}}, {"id": 649, "prop": "name", "attributes": {"content": "Would she become one of them?"}}, {"id": 650, "prop": "name", "attributes": {"content": "How would those who come after depict this life, one that seems too long for others to comprehend, yet far too hurried for herself?"}}, {"id": 651, "prop": "name", "attributes": {"content": "How would the other siblings react when they read those pages?"}}, {"id": 652, "prop": "name", "attributes": {"content": "..."}}, {"id": 653, "prop": "name", "attributes": {"content": "No. There will be no record of her. She knows it."}}, {"id": 654, "prop": "name", "attributes": {"content": "Of all the siblings, she is the one who has spent the most time with Wang."}}, {"id": 655, "prop": "name", "attributes": {"content": "She has given Wang ideas for his plans, helped him calculate the conditions and timing for Sui's elimination."}}, {"id": 656, "prop": "name", "attributes": {"content": "She can guess what is happening in the Tomb of Sui. The clear and distinct heartbeat has already told the full story."}}, {"id": 657, "prop": "name", "attributes": {"content": "There is no other way."}}, {"id": 658, "prop": "name", "attributes": {"content": "She must use her powers to erase the name—"}}, {"id": 659, "prop": "name", "attributes": {"content": "..."}}, {"id": 660, "prop": "name", "attributes": {"content": "She has spent much more time in the mortal realm than ordinary people."}}, {"id": 661, "prop": "name", "attributes": {"content": "Everyone dies. It is precisely the cycle of life and death that made possible the innumerable ways of life that have fascinated her, as well as her siblings."}}, {"id": 662, "prop": "name", "attributes": {"content": "But if death is such an unremarkable thing, like a wisp of smoke in the wind... what is living, truly?"}}, {"id": 663, "prop": "name", "attributes": {"content": "Light from the setting sun pours into the room, upon the countless history tomes, as though relentlessly poring through traces of the past."}}, {"id": 664, "prop": "name", "attributes": {"content": "Every word in these scrolls was written with tears of blood, but the only thing written on the last page is the word 'regret'."}}, {"id": 665, "prop": "dialog", "attributes": {}}, {"id": 666, "prop": "Dialog", "attributes": {}}, {"id": 667, "prop": "Blocker", "attributes": {"a": 1.0, "r": 0.0, "g": 0.0, "b": 0.0, "fadetime": 2.0, "block": "true"}}, {"id": 668, "prop": "curtain", "attributes": {"direction": 2.0, "fillfrom": 0.08, "fillto": 0.08, "fadetime": 0.0}}, {"id": 669, "prop": "curtain", "attributes": {"direction": 6.0, "fillfrom": 0.58, "fillto": 0.58, "fadetime": 0.0}}, {"id": 670, "prop": "Image", "attributes": {"image": "70_i18", "screenadapt": "coverall", "xScale": 1.0, "yScale": 1.0}}, {"id": 671, "prop": "ImageTween", "attributes": {"duration": 10.0, "block": "false"}}, {"id": 672, "prop": "Blocker", "attributes": {"a": 0.0, "r": 0.0, "g": 0.0, "b": 0.0, "fadetime": 2.0, "block": "true"}}, {"id": 673, "prop": "Sticker", "attributes": {"id": "st1", "multi": "true", "text": "The sun's rays by the window...", "x": 220.0, "y": 250.0, "alignment": "left", "size": 24.0, "delay": 0.001, "width": 400.0, "block": "false", "duration": 1.0}}, {"id": 674, "prop": "delay", "attributes": {"time": 2.0}}, {"id": 675, "prop": "Sticker", "attributes": {"id": "st2", "multi": "true", "text": "\\n\\n...How warm.", "x": 220.0, "y": 320.0, "alignment": "left", "size": 24.0, "delay": 0.001, "width": 400.0, "block": "true", "duration": 1.0}}, {"id": 676, "prop": "Sticker", "attributes": {"id": "st1", "duration": 1.0, "block": "false"}}, {"id": 677, "prop": "Sticker", "attributes": {"id": "st2", "duration": 1.0, "block": "false"}}, {"id": 678, "prop": "delay", "attributes": {"time": 1.5}}, {"id": 679, "prop": "name", "attributes": {"content": "But she does not walk towards the sunlight."}}, {"id": 680, "prop": "Dialog", "attributes": {}}, {"id": 681, "prop": "Blocker", "attributes": {"a": 1.0, "r": 0.0, "g": 0.0, "b": 0.0, "fadetime": 3.0, "block": "true"}}, {"id": 682, "prop": "charslot", "attributes": {}}, {"id": 683, "prop": "image", "attributes": {}}, {"id": 684, "prop": "name", "attributes": {"content": "She leaves the room."}}, {"id": 685, "prop": "name", "attributes": {"content": "Into the darkness of the tomb."}}, {"id": 686, "prop": "playsound", "attributes": {"key": "$d_avg_gatecloz"}}, {"id": 687, "prop": "Dialog", "attributes": {}}, {"id": 688, "prop": "curtain", "attributes": {}}, {"id": 689, "prop": "delay", "attributes": {"time": 1.0}}, {"id": 690, "prop": "bgeffect", "attributes": {}}, {"id": 691, "prop": "focusparam", "attributes": {"effect": "Grayscale", "blur": "false"}}, {"id": 692, "prop": "focusout", "attributes": {"duration": 0.0, "type": "bg", "from": 0.0, "to": 1.0, "block": "true"}}, {"id": 693, "prop": "Background", "attributes": {"image": "70_g7_suilingcore", "screenadapt": "coverall"}}, {"id": 694, "prop": "Blocker", "attributes": {"a": 0.0, "r": 0.0, "g": 0.0, "b": 0.0, "fadetime": 3.0, "block": "true"}}, {"id": 695, "prop": "charslot", "attributes": {"slot": "m", "name": "avg_2027_wang_1#4$1", "duration": 1.0}}, {"id": 696, "prop": "delay", "attributes": {"time": 2.0}}, {"id": 697, "prop": "name", "attributes": {"content": "...", "name": "Wang"}, "figure_art": "avg_2027_wang_1#4$1"}, {"id": 698, "prop": "charslot", "attributes": {"slot": "m", "focus": "n"}}, {"id": 699, "prop": "name", "attributes": {"content": "No words need to be said. Wang knows it is a fragment It has retrieved from his own memory, an image that he has never forgotten for even a moment in the last hundred and twenty years."}}, {"id": 700, "prop": "name", "attributes": {"content": "He lies exhausted on the ground. A hundred white pieces on the board have turned into blades that impale his chest, and he is slowly inundated by the pure white."}}, {"id": 701, "prop": "name", "attributes": {"content": "Until the golden light surrounds him."}}, {"id": 702, "prop": "charslot", "attributes": {"slot": "m", "name": "avg_2027_wang_1#5$1"}}, {"id": 703, "prop": "name", "attributes": {"content": "...I'm sorry.", "name": "Wang"}, "figure_art": "avg_2027_wang_1#5$1"}, {"id": 704, "prop": "name", "attributes": {"content": "Wait for me... wait for me to come back.", "name": "Wang"}, "figure_art": "avg_2027_wang_1#5$1"}, {"id": 705, "prop": "name", "attributes": {"content": "For you to come back.", "name": "Wang"}, "figure_art": "avg_2027_wang_1#5$1"}, {"id": 706, "prop": "charslot", "attributes": {"duration": 1.0}}, {"id": 707, "prop": "name", "attributes": {"content": "It was the other side of the dream, a place that he should not have been able to touch."}}, {"id": 708, "prop": "name", "attributes": {"content": "But she seems to notice him and turns around to look at him."}}, {"id": 709, "prop": "dialog", "attributes": {}}, {"id": 710, "prop": "charslot", "attributes": {}}, {"id": 711, "prop": "focusout", "attributes": {"duration": 0.0, "type": "char", "from": 0.0, "to": 1.0, "block": "true"}}, {"id": 712, "prop": "charslot", "attributes": {"slot": "m", "name": "avg_npc_2125_1#7$1", "duration": 1.0}}, {"id": 713, "prop": "delay", "attributes": {"time": 2.0}}, {"id": 714, "prop": "charslot", "attributes": {"slot": "r", "name": "avg_npc_2125_1#1$1", "posfrom": "-200,0", "posto": "-200,0", "duration": 1.0}}, {"id": 715, "prop": "delay", "attributes": {"time": 1.0}}, {"id": 716, "prop": "name", "attributes": {"content": "There is a faint smile on Jie's face, and she nods lightly."}}, {"id": 717, "prop": "bgeffect", "attributes": {"name": "$eb_glow_01", "fade": "true", "fadetime": 3.0, "layer": 1.0}}, {"id": 718, "prop": "charslot", "attributes": {"duration": 5.0}}, {"id": 719, "prop": "name", "attributes": {"content": "The light gushes from behind her, surrounding the figure, swallowing it, dissolving it..."}}, {"id": 720, "prop": "name", "attributes": {"content": "Sweeping away the dream realm, and revealing the true face of this place."}}, {"id": 721, "prop": "Dialog", "attributes": {}}, {"id": 722, "prop": "Blocker", "attributes": {"a": 1.0, "r": 0.0, "g": 0.0, "b": 0.0, "fadetime": 2.0, "block": "true"}}, {"id": 723, "prop": "charslot", "attributes": {}}, {"id": 724, "prop": "bgeffect", "attributes": {}}, {"id": 725, "prop": "focusout", "attributes": {"duration": 0.0, "type": "bg", "from": 1.0, "to": 0.0, "block": "true"}}, {"id": 726, "prop": "Blocker", "attributes": {"a": 0.0, "r": 0.0, "g": 0.0, "b": 0.0, "fadetime": 2.0, "block": "true"}}, {"id": 727, "prop": "Dialog", "attributes": {}}, {"id": 728, "prop": "delay", "attributes": {"time": 2.0}}, {"id": 729, "prop": "Blocker", "attributes": {"a": 1.0, "r": 0.0, "g": 0.0, "b": 0.0, "fadetime": 2.0, "block": "true"}}, {"id": 730, "prop": "bgeffect", "attributes": {}}, {"id": 731, "prop": "stopmusic", "attributes": {"fadetime": 2.0}}, {"id": 732, "prop": "hidecgitem", "attributes": {}}, {"id": 733, "prop": "Image", "attributes": {}}, {"id": 734, "prop": "charslot", "attributes": {}}, {"id": 735, "prop": "name", "attributes": {"content": ""}}], "OPTIONTRACE": true}